rcache/__init__.py
pyrcache-1.1.2.dist-info/LICENSE
pyrcache-1.1.2.dist-info/METADATA
pyrcache-1.1.2.dist-info/WHEEL
pyrcache-1.1.2.dist-info/top_level.txt
pyrcache-1.1.2.dist-info/RECORD
