Metadata-Version: 2.1
Name: pyrcache
Version: 1.1.2
Summary: Python API for accessing RedisCache
Home-page: https://github.com/yamaceay/pyrcache
Author: Yamac Eren Ay
Author-email: yamacerenay2001@gmail.com
License: UNKNOWN
Platform: UNKNOWN
Classifier: Programming Language :: Python :: 3
Classifier: License :: OSI Approved :: MIT License
Classifier: Operating System :: OS Independent
Requires-Python: >=3.8
Requires-Dist: requests (==2.28.1)
